{
    "exportTypes": {
        "exportTableTypes": [
            {
                "text": "CSV (.csv)",
                "code": "csv"    
            },
            {
                "text": "XLS (.xls)",
                "code": "xls"    
            },
            {
                "text": "XLSX (.xlsx)",
                "code": "xlsx"    
            }
        ],
        "exportDatasetTypes": [
            {
                "text": "XLS (.xls)",
                "code": "xls"    
            },
            {
                "text": "XLSX (.xlsx)",
                "code": "xlsx"    
            }
        ]
    }
}